pybunpro/__init__.py
pybunpro/__main__.py
pybunpro-3.0.0.dist-info/LICENSE
pybunpro-3.0.0.dist-info/METADATA
pybunpro-3.0.0.dist-info/WHEEL
pybunpro-3.0.0.dist-info/entry_points.txt
pybunpro-3.0.0.dist-info/top_level.txt
pybunpro-3.0.0.dist-info/RECORD
