Metadata-Version: 2.1
Name: pybunpro
Version: 3.0.0
Summary: REST client for Bunpro
Home-page: http://patrickayoup.github.io/pybunpro
Author: Patrick Ayoup
Author-email: patrick.ayoup@gmail.com
License: MIT
Keywords: rest client japanese grammar
Platform: UNKNOWN
Classifier: Programming Language :: Python :: 3
Classifier: License :: OSI Approved :: MIT License
Classifier: Operating System :: OS Independent
Requires-Dist: requests
Requires-Dist: marshmallow
Requires-Dist: Click
